odoo/addons/account_purchase_stock_report_non_billed/README.rst
odoo/addons/account_purchase_stock_report_non_billed/__init__.py
odoo/addons/account_purchase_stock_report_non_billed/__manifest__.py
odoo/addons/account_purchase_stock_report_non_billed/i18n/account_purchase_stock_report_non_billed.pot
odoo/addons/account_purchase_stock_report_non_billed/i18n/es.po
odoo/addons/account_purchase_stock_report_non_billed/models/__init__.py
odoo/addons/account_purchase_stock_report_non_billed/models/stock_move.py
odoo/addons/account_purchase_stock_report_non_billed/readme/CONTRIBUTORS.rst
odoo/addons/account_purchase_stock_report_non_billed/readme/DESCRIPTION.rst
odoo/addons/account_purchase_stock_report_non_billed/readme/USAGE.rst
odoo/addons/account_purchase_stock_report_non_billed/static/description/icon.png
odoo/addons/account_purchase_stock_report_non_billed/static/description/index.html
odoo/addons/account_purchase_stock_report_non_billed/tests/__init__.py
odoo/addons/account_purchase_stock_report_non_billed/tests/test_account_purchase_stock_report_non_billed.py
odoo/addons/account_purchase_stock_report_non_billed/wizard/__init__.py
odoo/addons/account_purchase_stock_report_non_billed/wizard/account_sale_stock_report_non_billed_wiz.py
odoo13_addon_account_purchase_stock_report_non_billed-13.0.1.1.0.dist-info/METADATA
odoo13_addon_account_purchase_stock_report_non_billed-13.0.1.1.0.dist-info/WHEEL
odoo13_addon_account_purchase_stock_report_non_billed-13.0.1.1.0.dist-info/top_level.txt
odoo13_addon_account_purchase_stock_report_non_billed-13.0.1.1.0.dist-info/RECORD
